{"name":"Nightfall","className":"DataModel","filePaths":["default.project.json"],"children":[{"name":"ReplicatedStorage","className":"ReplicatedStorage","children":[{"name":"ProfileService","className":"ModuleScript","filePaths":["Packages/ProfileService.lua"]},{"name":"Shared","className":"Folder","children":[{"name":"AnimationDatabase","className":"ModuleScript","filePaths":["src/shared\\AnimationDatabase.lua"]},{"name":"abilities","className":"Folder","children":[{"name":"Adrenaline","className":"ModuleScript","filePaths":["src/shared\\abilities\\Adrenaline.lua"]},{"name":"Ash","className":"ModuleScript","filePaths":["src/shared\\abilities\\Ash.lua"]},{"name":"BloodRage","className":"ModuleScript","filePaths":["src/shared\\abilities\\BloodRage.lua"]},{"name":"CripplingBlow","className":"ModuleScript","filePaths":["src/shared\\abilities\\CripplingBlow.lua"]},{"name":"Ember","className":"ModuleScript","filePaths":["src/shared\\abilities\\Ember.lua"]},{"name":"FrostShield","className":"ModuleScript","filePaths":["src/shared\\abilities\\FrostShield.lua"]},{"name":"Gale","className":"ModuleScript","filePaths":["src/shared\\abilities\\Gale.lua"]},{"name":"IronWill","className":"ModuleScript","filePaths":["src/shared\\abilities\\IronWill.lua"]},{"name":"Regenerate","className":"ModuleScript","filePaths":["src/shared\\abilities\\Regenerate.lua"]},{"name":"Stagger","className":"ModuleScript","filePaths":["src/shared\\abilities\\Stagger.lua"]},{"name":"Swiftness","className":"ModuleScript","filePaths":["src/shared\\abilities\\Swiftness.lua"]},{"name":"Tide","className":"ModuleScript","filePaths":["src/shared\\abilities\\Tide.lua"]},{"name":"Void","className":"ModuleScript","filePaths":["src/shared\\abilities\\Void.lua"]}]},{"name":"combat","className":"Folder","children":[{"name":"states","className":"Folder","children":[{"name":"AttackState","className":"ModuleScript","filePaths":["src/shared\\combat\\states\\AttackState.lua"]},{"name":"BlockState","className":"ModuleScript","filePaths":["src/shared\\combat\\states\\BlockState.lua"]},{"name":"IdleState","className":"ModuleScript","filePaths":["src/shared\\combat\\states\\IdleState.lua"]},{"name":"StunnedState","className":"ModuleScript","filePaths":["src/shared\\combat\\states\\StunnedState.lua"]}]}]},{"name":"items","className":"Folder","children":[{"name":"TrainingTools","className":"Folder","children":[{"name":"training_tool_agility_common","className":"ModuleScript","filePaths":["src/shared\\items\\TrainingTools\\training_tool_agility_common.lua"]},{"name":"training_tool_charisma_common","className":"ModuleScript","filePaths":["src/shared\\items\\TrainingTools\\training_tool_charisma_common.lua"]},{"name":"training_tool_fortitude_common","className":"ModuleScript","filePaths":["src/shared\\items\\TrainingTools\\training_tool_fortitude_common.lua"]},{"name":"training_tool_fortitude_uncommon","className":"ModuleScript","filePaths":["src/shared\\items\\TrainingTools\\training_tool_fortitude_uncommon.lua"]},{"name":"training_tool_intelligence_common","className":"ModuleScript","filePaths":["src/shared\\items\\TrainingTools\\training_tool_intelligence_common.lua"]},{"name":"training_tool_strength_common","className":"ModuleScript","filePaths":["src/shared\\items\\TrainingTools\\training_tool_strength_common.lua"]},{"name":"training_tool_strength_rare","className":"ModuleScript","filePaths":["src/shared\\items\\TrainingTools\\training_tool_strength_rare.lua"]},{"name":"training_tool_strength_uncommon","className":"ModuleScript","filePaths":["src/shared\\items\\TrainingTools\\training_tool_strength_uncommon.lua"]},{"name":"training_tool_willpower_common","className":"ModuleScript","filePaths":["src/shared\\items\\TrainingTools\\training_tool_willpower_common.lua"]}]}]},{"name":"modules","className":"Folder","children":[{"name":"AbilityRegistry","className":"ModuleScript","filePaths":["src/shared\\modules\\AbilityRegistry.lua"]},{"name":"AnimationLoader","className":"ModuleScript","filePaths":["src/shared\\modules\\AnimationLoader.lua"]},{"name":"AspectRegistry","className":"ModuleScript","filePaths":["src/shared\\modules\\AspectRegistry.lua"]},{"name":"CombatBlackboard","className":"ModuleScript","filePaths":["src/shared\\modules\\CombatBlackboard.lua"]},{"name":"DebugSettings","className":"ModuleScript","filePaths":["src/shared\\modules\\DebugSettings.lua"]},{"name":"DisciplineConfig","className":"ModuleScript","filePaths":["src/shared\\modules\\DisciplineConfig.lua"]},{"name":"HitboxService","className":"ModuleScript","filePaths":["src/shared\\modules\\HitboxService.lua"]},{"name":"ItemRegistry","className":"ModuleScript","filePaths":["src/shared\\modules\\ItemRegistry.lua"]},{"name":"Loader","className":"ModuleScript","filePaths":["src/shared\\modules\\Loader.lua"]},{"name":"LootLibrary","className":"ModuleScript","filePaths":["src/shared\\modules\\LootLibrary.lua"]},{"name":"MovementBlackboard","className":"ModuleScript","filePaths":["src/shared\\modules\\MovementBlackboard.lua"]},{"name":"MovementConfig","className":"ModuleScript","filePaths":["src/shared\\modules\\MovementConfig.lua"]},{"name":"StateService","className":"ModuleScript","filePaths":["src/shared\\modules\\StateService.lua"]},{"name":"Utils","className":"ModuleScript","filePaths":["src/shared\\modules\\Utils.lua"]},{"name":"WeaponRegistry","className":"ModuleScript","filePaths":["src/shared\\modules\\WeaponRegistry.lua"]},{"name":"WeaponValidator","className":"ModuleScript","filePaths":["src/shared\\modules\\WeaponValidator.lua"]}]},{"name":"movement","className":"Folder","children":[{"name":"StateContext","className":"ModuleScript","filePaths":["src/shared\\movement\\StateContext.lua"]},{"name":"states","className":"Folder","children":[{"name":"ClimbState","className":"ModuleScript","filePaths":["src/shared\\movement\\states\\ClimbState.lua"]},{"name":"IdleState","className":"ModuleScript","filePaths":["src/shared\\movement\\states\\IdleState.lua"]},{"name":"JumpState","className":"ModuleScript","filePaths":["src/shared\\movement\\states\\JumpState.lua"]},{"name":"LedgeCatchState","className":"ModuleScript","filePaths":["src/shared\\movement\\states\\LedgeCatchState.lua"]},{"name":"SlideState","className":"ModuleScript","filePaths":["src/shared\\movement\\states\\SlideState.lua"]},{"name":"SprintState","className":"ModuleScript","filePaths":["src/shared\\movement\\states\\SprintState.lua"]},{"name":"VaultState","className":"ModuleScript","filePaths":["src/shared\\movement\\states\\VaultState.lua"]},{"name":"WalkState","className":"ModuleScript","filePaths":["src/shared\\movement\\states\\WalkState.lua"]},{"name":"WallBoostState","className":"ModuleScript","filePaths":["src/shared\\movement\\states\\WallBoostState.lua"]},{"name":"WallRunState","className":"ModuleScript","filePaths":["src/shared\\movement\\states\\WallRunState.lua"]}]}]},{"name":"network","className":"Folder","children":[{"name":"NetworkProvider","className":"ModuleScript","filePaths":["src/shared\\network\\NetworkProvider.lua"]}]},{"name":"types","className":"Folder","children":[{"name":"ActionTypes","className":"ModuleScript","filePaths":["src/shared\\types\\ActionTypes.lua"]},{"name":"AspectTypes","className":"ModuleScript","filePaths":["src/shared\\types\\AspectTypes.lua"]},{"name":"CodexTypes","className":"ModuleScript","filePaths":["src/shared\\types\\CodexTypes.lua"]},{"name":"DummyData","className":"ModuleScript","filePaths":["src/shared\\types\\DummyData.lua"]},{"name":"EffectTypes","className":"ModuleScript","filePaths":["src/shared\\types\\EffectTypes.lua"]},{"name":"HitboxTypes","className":"ModuleScript","filePaths":["src/shared\\types\\HitboxTypes.lua"]},{"name":"HollowedTypes","className":"ModuleScript","filePaths":["src/shared\\types\\HollowedTypes.lua"]},{"name":"InventoryTypes","className":"ModuleScript","filePaths":["src/shared\\types\\InventoryTypes.lua"]},{"name":"ItemTypes","className":"ModuleScript","filePaths":["src/shared\\types\\ItemTypes.lua"]},{"name":"NetworkTypes","className":"ModuleScript","filePaths":["src/shared\\types\\NetworkTypes.lua"]},{"name":"PlayerData","className":"ModuleScript","filePaths":["src/shared\\types\\PlayerData.lua"]},{"name":"ProgressionTypes","className":"ModuleScript","filePaths":["src/shared\\types\\ProgressionTypes.lua"]},{"name":"WeaponTypes","className":"ModuleScript","filePaths":["src/shared\\types\\WeaponTypes.lua"]}]},{"name":"weapons","className":"Folder","children":[{"name":"Fists","className":"ModuleScript","filePaths":["src/shared\\weapons\\Fists.lua"]},{"name":"IronSword","className":"ModuleScript","filePaths":["src/shared\\weapons\\IronSword.lua"]},{"name":"ResonantStaff","className":"ModuleScript","filePaths":["src/shared\\weapons\\ResonantStaff.lua"]},{"name":"SilhouetteDagger","className":"ModuleScript","filePaths":["src/shared\\weapons\\SilhouetteDagger.lua"]},{"name":"Sword","className":"Folder","children":[{"name":"IronSabre","className":"ModuleScript","filePaths":["src/shared\\weapons\\Sword\\IronSabre.lua"]}]},{"name":"WaywardSword","className":"ModuleScript","filePaths":["src/shared\\weapons\\WaywardSword.lua"]}]}]},{"name":"Signal","className":"ModuleScript","filePaths":["Packages/Signal.lua"]}]},{"name":"ServerScriptService","className":"ServerScriptService","children":[{"name":"Server","className":"Folder","children":[{"name":"DevWorldBootstrap","className":"Script","filePaths":["src/server\\DevWorldBootstrap.server.lua"]},{"name":"ServerInit","className":"Script","filePaths":["src/server\\ServerInit.server.lua"]},{"name":"runtime","className":"ModuleScript","filePaths":["src/server\\runtime\\init.lua"]},{"name":"services","className":"Folder","children":[{"name":"AbilitySystem","className":"ModuleScript","filePaths":["src/server\\services\\AbilitySystem.lua"]},{"name":"AbilityValidator","className":"ModuleScript","filePaths":["src/server\\services\\AbilityValidator.lua"]},{"name":"AspectService","className":"ModuleScript","filePaths":["src/server\\services\\AspectService.lua"]},{"name":"CombatService","className":"ModuleScript","filePaths":["src/server\\services\\CombatService.lua"]},{"name":"DataService","className":"ModuleScript","filePaths":["src/server\\services\\DataService.lua"]},{"name":"DeathService","className":"ModuleScript","filePaths":["src/server\\services\\DeathService.lua"]},{"name":"DefenseService","className":"ModuleScript","filePaths":["src/server\\services\\DefenseService.lua"]},{"name":"DummyService","className":"ModuleScript","filePaths":["src/server\\services\\DummyService.lua"]},{"name":"EffectHandlers","className":"ModuleScript","filePaths":["src/server\\services\\EffectHandlers.lua"]},{"name":"EffectRunner","className":"ModuleScript","filePaths":["src/server\\services\\EffectRunner.lua"]},{"name":"HollowedService","className":"ModuleScript","filePaths":["src/server\\services\\HollowedService.lua"]},{"name":"InventoryService","className":"ModuleScript","filePaths":["src/server\\services\\InventoryService.lua"]},{"name":"MovementService","className":"ModuleScript","filePaths":["src/server\\services\\MovementService.lua"]},{"name":"NetworkService","className":"ModuleScript","filePaths":["src/server\\services\\NetworkService.lua"]},{"name":"PassiveSystem","className":"ModuleScript","filePaths":["src/server\\services\\PassiveSystem.lua"]},{"name":"PostureService","className":"ModuleScript","filePaths":["src/server\\services\\PostureService.lua"]},{"name":"ProgressionService","className":"ModuleScript","filePaths":["src/server\\services\\ProgressionService.lua"]},{"name":"StateSyncService","className":"ModuleScript","filePaths":["src/server\\services\\StateSyncService.lua"]},{"name":"TrainingToolService","className":"ModuleScript","filePaths":["src/server\\services\\TrainingToolService.lua"]},{"name":"WeaponService","className":"ModuleScript","filePaths":["src/server\\services\\WeaponService.lua"]},{"name":"WitnessService","className":"ModuleScript","filePaths":["src/server\\services\\WitnessService.lua"]},{"name":"ZoneService","className":"ModuleScript","filePaths":["src/server\\services\\ZoneService.lua"]}]}]},{"name":"tests","className":"Folder","children":[{"name":"unit","className":"Folder","children":[{"name":"ActionController.test","className":"ModuleScript","filePaths":["tests\\unit\\ActionController.test.lua"]},{"name":"AnimationLoader.test","className":"ModuleScript","filePaths":["tests\\unit\\AnimationLoader.test.lua"]},{"name":"AshExpression.test","className":"ModuleScript","filePaths":["tests\\unit\\AshExpression.test.lua"]},{"name":"AspectController.test","className":"ModuleScript","filePaths":["tests\\unit\\AspectController.test.lua"]},{"name":"AspectService.test","className":"ModuleScript","filePaths":["tests\\unit\\AspectService.test.lua"]},{"name":"AspectSwitching.test","className":"ModuleScript","filePaths":["tests\\unit\\AspectSwitching.test.lua"]},{"name":"CombatController.test","className":"ModuleScript","filePaths":["tests\\unit\\CombatController.test.lua"]},{"name":"CombatService.test","className":"ModuleScript","filePaths":["tests\\unit\\CombatService.test.lua"]},{"name":"DummyService.test","className":"ModuleScript","filePaths":["tests\\unit\\DummyService.test.lua"]},{"name":"EmberExpression.test","className":"ModuleScript","filePaths":["tests\\unit\\EmberExpression.test.lua"]},{"name":"GaleExpression.test","className":"ModuleScript","filePaths":["tests\\unit\\GaleExpression.test.lua"]},{"name":"HollowedService.test","className":"ModuleScript","filePaths":["tests\\unit\\HollowedService.test.lua"]},{"name":"InventoryController.test","className":"ModuleScript","filePaths":["tests\\unit\\InventoryController.test.lua"]},{"name":"InventoryService.test","className":"ModuleScript","filePaths":["tests\\unit\\InventoryService.test.lua"]},{"name":"ItemTypes.test","className":"ModuleScript","filePaths":["tests\\unit\\ItemTypes.test.lua"]},{"name":"MovementController.test","className":"ModuleScript","filePaths":["tests\\unit\\MovementController.test.lua"]},{"name":"MovementControllerDisc.test","className":"ModuleScript","filePaths":["tests\\unit\\MovementControllerDisc.test.lua"]},{"name":"MovementService.test","className":"ModuleScript","filePaths":["tests\\unit\\MovementService.test.lua"]},{"name":"NetworkProvider.test","className":"ModuleScript","filePaths":["tests\\unit\\NetworkProvider.test.lua"]},{"name":"PostureService.test","className":"ModuleScript","filePaths":["tests\\unit\\PostureService.test.lua"]},{"name":"ProgressionService.test","className":"ModuleScript","filePaths":["tests\\unit\\ProgressionService.test.lua"]},{"name":"TideExpression.test","className":"ModuleScript","filePaths":["tests\\unit\\TideExpression.test.lua"]},{"name":"VoidExpression.test","className":"ModuleScript","filePaths":["tests\\unit\\VoidExpression.test.lua"]},{"name":"WeaponRegistry.test","className":"ModuleScript","filePaths":["tests\\unit\\WeaponRegistry.test.lua"]},{"name":"WeaponService.test","className":"ModuleScript","filePaths":["tests\\unit\\WeaponService.test.lua"]},{"name":"ZoneService.test","className":"ModuleScript","filePaths":["tests\\unit\\ZoneService.test.lua"]},{"name":"ZoneTriggerIgnore.test","className":"ModuleScript","filePaths":["tests\\unit\\ZoneTriggerIgnore.test.lua"]}]}]}]},{"name":"StarterPlayer","className":"StarterPlayer","children":[{"name":"StarterPlayerScripts","className":"StarterPlayerScripts","children":[{"name":"Client","className":"Folder","children":[{"name":"ClientInit","className":"LocalScript","filePaths":["src/client\\ClientInit.client.lua"]},{"name":"controllers","className":"Folder","children":[{"name":"ActionController","className":"ModuleScript","filePaths":["src/client\\controllers\\ActionController.lua"]},{"name":"AspectController","className":"ModuleScript","filePaths":["src/client\\controllers\\AspectController.lua"]},{"name":"CharacterCreationController","className":"ModuleScript","filePaths":["src/client\\controllers\\CharacterCreationController.lua"]},{"name":"CombatController","className":"ModuleScript","filePaths":["src/client\\controllers\\CombatController.lua"]},{"name":"CombatFeedbackUI","className":"ModuleScript","filePaths":["src/client\\controllers\\CombatFeedbackUI.lua"]},{"name":"DeathController","className":"ModuleScript","filePaths":["src/client\\controllers\\DeathController.lua"]},{"name":"DummyController","className":"ModuleScript","filePaths":["src/client\\controllers\\DummyController.lua"]},{"name":"EmberPointController","className":"ModuleScript","filePaths":["src/client\\controllers\\EmberPointController.lua"]},{"name":"InventoryController","className":"ModuleScript","filePaths":["src/client\\controllers\\InventoryController.lua"]},{"name":"LoadingController","className":"ModuleScript","filePaths":["src/client\\controllers\\LoadingController.lua"]},{"name":"MovementController","className":"ModuleScript","filePaths":["src/client\\controllers\\MovementController.lua"]},{"name":"NetworkController","className":"ModuleScript","filePaths":["src/client\\controllers\\NetworkController.lua"]},{"name":"PlayerHUDController","className":"ModuleScript","filePaths":["src/client\\controllers\\PlayerHUDController.lua"]},{"name":"ProgressionController","className":"ModuleScript","filePaths":["src/client\\controllers\\ProgressionController.lua"]},{"name":"StateSyncController","className":"ModuleScript","filePaths":["src/client\\controllers\\StateSyncController.lua"]},{"name":"WeaponController","className":"ModuleScript","filePaths":["src/client\\controllers\\WeaponController.lua"]},{"name":"WeaponEffectsController","className":"ModuleScript","filePaths":["src/client\\controllers\\WeaponEffectsController.lua"]},{"name":"WitnessController","className":"ModuleScript","filePaths":["src/client\\controllers\\WitnessController.lua"]}]},{"name":"modules","className":"Folder","children":[{"name":"DebugInput","className":"ModuleScript","filePaths":["src/client\\modules\\DebugInput.lua"]},{"name":"UIBinding","className":"ModuleScript","filePaths":["src/client\\modules\\UIBinding.lua"]}]},{"name":"runtime","className":"ModuleScript","filePaths":["src/client\\runtime\\init.lua"]}]}]}]}]}